{
	"format_version": "1.8.0",
	"animations": {
		"animation.infuser.idle": {
			"loop": true,
			"animation_length": 1.5,
			"bones": {
				"thingy1": {
					"rotation": {
						"0.0": {
							"vector": [5, 0, 0],
							"easing": "easeInOutSine"
						},
						"0.75": {
							"vector": [0, 0, 0]
						},
						"1.5": {
							"vector": [5, 0, 0],
							"easing": "easeInOutSine"
						}
					}
				},
				"thingy2": {
					"rotation": {
						"0.0": {
							"vector": [-5, 0, 0],
							"easing": "easeInOutSine"
						},
						"0.75": {
							"vector": [0, 0, 0]
						},
						"1.5": {
							"vector": [-5, 0, 0],
							"easing": "easeInOutSine"
						}
					}
				},
				"thingy3": {
					"rotation": {
						"0.0": {
							"vector": [0, 0, -5],
							"easing": "easeInOutSine"
						},
						"0.75": {
							"vector": [0, 0, 0]
						},
						"1.5": {
							"vector": [0, 0, -5],
							"easing": "easeInOutSine"
						}
					}
				},
				"thingy4": {
					"rotation": {
						"0.0": {
							"vector": [0, 0, 5],
							"easing": "easeInOutSine"
						},
						"0.75": {
							"vector": [0, 0, 0]
						},
						"1.5": {
							"vector": [0, 0, 5],
							"easing": "easeInOutSine"
						}
					}
				},
				"thingy5": {
					"rotation": {
						"0.0": {
							"vector": [0, 0, 0]
						},
						"0.75": {
							"vector": [5, 0, 0],
							"easing": "easeInOutSine"
						},
						"1.5": {
							"vector": [0, 0, 0],
							"easing": "easeInOutSine"
						}
					}
				},
				"thingy6": {
					"rotation": {
						"0.0": {
							"vector": [0, 0, 0]
						},
						"0.75": {
							"vector": [-5, 0, 0],
							"easing": "easeInOutSine"
						},
						"1.5": {
							"vector": [0, 0, 0],
							"easing": "easeInOutSine"
						}
					}
				},
				"thingy7": {
					"rotation": {
						"0.0": {
							"vector": [0, 0, 0]
						},
						"0.75": {
							"vector": [0, 0, -5],
							"easing": "easeInOutSine"
						},
						"1.5": {
							"vector": [0, 0, 0],
							"easing": "easeInOutSine"
						}
					}
				},
				"thingy8": {
					"rotation": {
						"0.0": {
							"vector": [0, 0, 0]
						},
						"0.75": {
							"vector": [0, 0, 5],
							"easing": "easeInOutSine"
						},
						"1.5": {
							"vector": [0, 0, 0],
							"easing": "easeInOutSine"
						}
					}
				}
			}
		},
		"animation.infuser.active": {
			"loop": true,
			"animation_length": 0.5,
			"bones": {
				"thingy1": {
					"rotation": {
						"0.0": {
							"vector": [5, 0, 0],
							"easing": "easeInOutSine"
						},
						"0.25": {
							"vector": [0, 0, 0]
						},
						"0.5": {
							"vector": [5, 0, 0],
							"easing": "easeInOutSine"
						}
					}
				},
				"thingy2": {
					"rotation": {
						"0.0": {
							"vector": [-5, 0, 0],
							"easing": "easeInOutSine"
						},
						"0.25": {
							"vector": [0, 0, 0]
						},
						"0.5": {
							"vector": [-5, 0, 0],
							"easing": "easeInOutSine"
						}
					}
				},
				"thingy3": {
					"rotation": {
						"0.0": {
							"vector": [0, 0, -5],
							"easing": "easeInOutSine"
						},
						"0.25": {
							"vector": [0, 0, 0]
						},
						"0.5": {
							"vector": [0, 0, -5],
							"easing": "easeInOutSine"
						}
					}
				},
				"thingy4": {
					"rotation": {
						"0.0": {
							"vector": [0, 0, 5],
							"easing": "easeInOutSine"
						},
						"0.25": {
							"vector": [0, 0, 0]
						},
						"0.5": {
							"vector": [0, 0, 5],
							"easing": "easeInOutSine"
						}
					}
				},
				"thingy5": {
					"rotation": {
						"0.0": {
							"vector": [0, 0, 0]
						},
						"0.25": {
							"vector": [5, 0, 0],
							"easing": "easeInOutSine"
						},
						"0.5": {
							"vector": [0, 0, 0],
							"easing": "easeInOutSine"
						}
					}
				},
				"thingy6": {
					"rotation": {
						"0.0": {
							"vector": [0, 0, 0]
						},
						"0.25": {
							"vector": [-5, 0, 0],
							"easing": "easeInOutSine"
						},
						"0.5": {
							"vector": [0, 0, 0],
							"easing": "easeInOutSine"
						}
					}
				},
				"thingy7": {
					"rotation": {
						"0.0": {
							"vector": [0, 0, 0]
						},
						"0.25": {
							"vector": [0, 0, -5],
							"easing": "easeInOutSine"
						},
						"0.5": {
							"vector": [0, 0, 0],
							"easing": "easeInOutSine"
						}
					}
				},
				"thingy8": {
					"rotation": {
						"0.0": {
							"vector": [0, 0, 0]
						},
						"0.25": {
							"vector": [0, 0, 5],
							"easing": "easeInOutSine"
						},
						"0.5": {
							"vector": [0, 0, 0],
							"easing": "easeInOutSine"
						}
					}
				}
			}
		},
		"animation.infuser.deactivated": {
			"loop": true,
			"animation_length": 6.66667,
			"bones": {
				"thingy1": {
					"rotation": {
						"vector": [30, 0, 0]
					}
				},
				"thingy2": {
					"rotation": {
						"vector": [-30, 0, 0]
					}
				},
				"thingy3": {
					"rotation": {
						"vector": [0, 0, -30]
					}
				},
				"thingy4": {
					"rotation": {
						"vector": [0, 0, 30]
					}
				},
				"thingy5": {
					"rotation": {
						"vector": [30, 0, 0]
					}
				},
				"thingy6": {
					"rotation": {
						"vector": [-30, 0, 0]
					}
				},
				"thingy7": {
					"rotation": {
						"vector": [0, 0, -30]
					}
				},
				"thingy8": {
					"rotation": {
						"vector": [0, 0, 30]
					}
				}
			}
		}
	},
	"geckolib_format_version": 2
}